pyrdf4j/__init__.py
pyrdf4j/api_base.py
pyrdf4j/api_graph.py
pyrdf4j/api_repo.py
pyrdf4j/constants.py
pyrdf4j/errors.py
pyrdf4j/rdf4j.py
pyrdf4j/repo_type_templates/memory-customrule.ttl
pyrdf4j/repo_type_templates/memory-lucene.ttl
pyrdf4j/repo_type_templates/memory-rdfs-dt.ttl
pyrdf4j/repo_type_templates/memory-rdfs-legacy.ttl
pyrdf4j/repo_type_templates/memory-rdfs-lucene.ttl
pyrdf4j/repo_type_templates/memory-rdfs.ttl
pyrdf4j/repo_type_templates/memory-shacl.ttl
pyrdf4j/repo_type_templates/memory-spin-rdfs-lucene.ttl
pyrdf4j/repo_type_templates/memory-spin-rdfs.ttl
pyrdf4j/repo_type_templates/memory-spin.ttl
pyrdf4j/repo_type_templates/memory.ttl
pyrdf4j/repo_type_templates/native-customrule.ttl
pyrdf4j/repo_type_templates/native-lucene.ttl
pyrdf4j/repo_type_templates/native-rdfs-dt.ttl
pyrdf4j/repo_type_templates/native-rdfs-lucene.ttl
pyrdf4j/repo_type_templates/native-rdfs.ttl
pyrdf4j/repo_type_templates/native-shacl.ttl
pyrdf4j/repo_type_templates/native-spin-rdfs-lucene.ttl
pyrdf4j/repo_type_templates/native-spin-rdfs.ttl
pyrdf4j/repo_type_templates/native-spin.ttl
pyrdf4j/repo_type_templates/native.ttl
pyrdf4j/repo_type_templates/remote.ttl
pyrdf4j/repo_type_templates/sparql.ttl
pyrdf4j/repo_types.py
pyrdf4j/server.py
pyrdf4j/sparql.py
pyrdf4j/util.py
pyrdf4j-0.1.1.dist-info/LICENSE
pyrdf4j-0.1.1.dist-info/METADATA
pyrdf4j-0.1.1.dist-info/WHEEL
pyrdf4j-0.1.1.dist-info/RECORD
