Metadata-Version: 2.1
Name: pyrdf4j
Version: 0.1.1
Summary: 
Author: volker
Author-email: volker.jaenisch@inqbus.de
Requires-Python: >=3.7,<4.0
Classifier: Programming Language :: Python :: 3
Classifier: Programming Language :: Python :: 3.7
Classifier: Programming Language :: Python :: 3.8
Classifier: Programming Language :: Python :: 3.9
Classifier: Programming Language :: Python :: 3.10
Classifier: Programming Language :: Python :: 3.11
Classifier: Programming Language :: Python :: 3.12
Requires-Dist: SPARQLWrapper (>=2.0.0,<3.0.0)
